tts_webui_extension/fireredtts2/__init__.py
tts_webui_extension/fireredtts2/api.py
tts_webui_extension/fireredtts2/api_dialogue.py
tts_webui_extension/fireredtts2/dialogue_ui.py
tts_webui_extension/fireredtts2/main.py
tts_webui_extension/fireredtts2/tts_ui.py
tts_webui_extension_fireredtts2-0.0.2.dist-info/licenses/LICENSE
tts_webui_extension_fireredtts2-0.0.2.dist-info/METADATA
tts_webui_extension_fireredtts2-0.0.2.dist-info/WHEEL
tts_webui_extension_fireredtts2-0.0.2.dist-info/top_level.txt
tts_webui_extension_fireredtts2-0.0.2.dist-info/RECORD
